README.rst
pyproject.toml
setup.py
splg/__init__.py
splg/__main__.py
splg/cache.py
splg/client.py
splg/disk.py
splg/error.py
splg/event.py
splg/find.py
splg/fleet.py
splg/object.py
splg/reactor.py
splg/thread.py
splg/timer.py
splg/utils.py
splg/workdir.py
splg.egg-info/PKG-INFO
splg.egg-info/SOURCES.txt
splg.egg-info/dependency_links.txt
splg.egg-info/entry_points.txt
splg.egg-info/top_level.txt
splg/html/about.html
splg/html/evidence.html
splg/html/genindex-all.html
splg/html/genindex.html
splg/html/guilty.html
splg/html/index.html
splg/html/manual.html
splg/html/objects.inv
splg/html/reconsider.html
splg/html/request.html
splg/html/robots.txt
splg/html/search.html
splg/html/searchindex.js
splg/html/writings.html
splg/html/_images/ECHAabilify.png
splg/html/_images/ECHAclozapine.png
splg/html/_images/ECHAhaldol.png
splg/html/_images/ECHAzyprexa.png
splg/html/_images/OTP111.png
splg/html/_images/OTP222.png
splg/html/_images/ack3.png
splg/html/_images/bevestigd.jpg
splg/html/_images/genocide.png
splg/html/_images/informed.jpg
splg/html/_images/kamer2.png
splg/html/_images/skull3.png
splg/html/_static/alabaster.css
splg/html/_static/basic.css
splg/html/_static/custom.css
splg/html/_static/doctools.js
splg/html/_static/documentation_options.js
splg/html/_static/file.png
splg/html/_static/genocide.css
splg/html/_static/language_data.js
splg/html/_static/minus.png
splg/html/_static/opensearch.xml
splg/html/_static/plus.png
splg/html/_static/pygments.css
splg/html/_static/searchtools.js
splg/html/_static/sitemap.xml
splg/html/_static/skull3.png
splg/html/_static/sphinx_highlight.js
splg/modules/__init__.py
splg/modules/pth.py
splg/modules/req.py
splg/modules/slg.py
splg/modules/tbl.py
splg/pdf/EM_Ack_OTP-CR-117_19.pdf
splg/pdf/EM_T04_OTP-CR-117_19.pdf
splg/pdf/EM_T07_OTP-CR-117_19_001.pdf
splg/pdf/Kamer.pdf
splg/pdf/Rome-Statute.pdf
splg/pdf/bevestigd.pdf