Metadata-Version: 2.1
Name: splg
Version: 101
Summary: Stop Poison Law Genocide (SPLG)
Author-email: Bart Thate <bthate@dds.nl>
License: Public Domain
Project-URL: home, https://pypi.org/project/splg
Project-URL: bugs, https://github.com/bthate/splg/issues
Project-URL: source, https://github.com/bthate/splg
Classifier: Development Status :: 3 - Alpha
Classifier: License :: Public Domain
Classifier: Operating System :: Unix
Classifier: Programming Language :: Python
Classifier: Topic :: Utilities
